macest/__init__.py
macest/__version__.py
macest/model_selection.py
macest/classification/__init__.py
macest/classification/metrics.py
macest/classification/models.py
macest/classification/plots.py
macest/classification/utils.py
macest/regression/__init__.py
macest/regression/metrics.py
macest/regression/models.py
macest/regression/plots.py
macest-1.0.0.dist-info/LICENSE.txt
macest-1.0.0.dist-info/METADATA
macest-1.0.0.dist-info/WHEEL
macest-1.0.0.dist-info/top_level.txt
macest-1.0.0.dist-info/RECORD
