Metadata-Version: 2.1
Name: macest
Version: 1.0.0
Summary: UNKNOWN
Home-page: https://github.com/oracle/macest
Author: Mathew Rowe @ Oracle
Author-email: matthew.r.rowe@oracle.com
License: ??
Platform: UNKNOWN
Requires-Dist: matplotlib (==3.1.1)
Requires-Dist: numpy (==1.19.0)
Requires-Dist: pandas (==1.0.3)
Requires-Dist: scikit-learn (==0.22.1)
Requires-Dist: scipy (==1.4.1)
Requires-Dist: seaborn (==0.11.0)
Requires-Dist: nmslib (==2.0.6)
Requires-Dist: typing-extensions (==3.7.4.3)
